{
    "即時": [
        {
            "img_url": "https://pgw.udn.com.tw/gw/photo.php?u=https://uc.udn.com.tw/photo/t3/2026/05/25/34978478.png&M=1&s=Y&x=0&y=0&sw=1280&sh=853&exp=3600&w=300",
            "title": "荷莫茲將開放？伊朗：海峽管理不會恢復到戰前狀態",
            "link": "https://udn.com//news/story/124061/9523256?from=udn-ch1_breaknews-1-0-news",
            "time": "2026-05-25 07:59"
        },
        {
            "img_url": "https://pgw.udn.com.tw/gw/photo.php?u=https://uc.udn.com.tw/photo/t3/2026/05/25/34978475.jpg&M=1&s=Y&x=1&y=56&sw=1279&sh=852&exp=3600&w=300",
            "title": "瑪家鄉代下村考察傻眼 嘆「果樹不長果長垃圾！」",
            "link": "https://udn.com//news/story/7327/9523254?from=udn-ch1_breaknews-1-0-news",
            "time": "2026-05-25 07:57"
        },
        {
            "img_url": "https://pgw.udn.com.tw/gw/photo.php?u=https://uc.udn.com.tw/photo/t3/2026/05/25/34978474.jpg&M=1&s=Y&x=0&y=0&sw=1280&sh=853&exp=3600&w=300",
            "title": "美伊核問題再度喬不攏 川普：不急著達成協議 維持封鎖伊朗港口",
            "link": "https://udn.com//news/story/6809/9523253?from=udn-ch1_breaknews-1-0-news",
            "time": "2026-05-25 07:55"
        },
        {
            "img_url": "https://pgw.udn.com.tw/gw/photo.php?u=https://uc.udn.com.tw/photo/t3/2026/05/25/34978473.jpg&M=1&s=Y&x=0&y=0&sw=1280&sh=853&exp=3600&w=300",
            "title": "全台烤番薯！今高溫恐飆38度以上 13縣市亮高溫燈號",
            "link": "https://udn.com//news/story/7266/9523251?from=udn-ch1_breaknews-1-0-news",
            "time": "2026-05-25 07:48"
        },
        {
            "img_url": "https://pgw.udn.com.tw/gw/photo.php?u=https://uc.udn.com.tw/photo/t3/2026/05/25/34978466.jpg&M=1&s=Y&x=0&y=0&sw=1255&sh=837&exp=3600&w=300",
            "title": "出價115億歐元遭拒 Uber擬加碼收購foodpanda母公司Delivery Hero",
            "link": "https://udn.com//news/story/6811/9523244?from=udn-ch1_breaknews-1-0-news",
            "time": "2026-05-25 07:41"
        }
    ]
}