{
    "即時": [
        {
            "img_url": "https://pgw.udn.com.tw/gw/photo.php?u=https://uc.udn.com.tw/photo/2025/01/17/realtime/31308625.jpg&s=Y&x=0&y=0&sw=4046&sh=2698&exp=3600&w=300",
            "title": "美中台博弈／迎接川普2.0 是否「親中遠美」日本陷抉擇",
            "link": "https://udn.com//news/story/6809/8497378?from=udn-ch1_breaknews-1-0-news",
            "time": "2025-01-18 07:00"
        },
        {
            "img_url": "https://pgw.udn.com.tw/gw/photo.php?u=https://uc.udn.com.tw/photo/2025/01/18/realtime/31313283.jpg&s=Y&x=132&y=0&sw=1440&sh=960&exp=3600&w=300",
            "title": "基隆愛四路廟口夜市至仁二路騎樓整平 3月展開改善通行",
            "link": "https://udn.com//news/story/7328/8498280?from=udn-ch1_breaknews-1-0-news",
            "time": "2025-01-18 06:59"
        },
        {
            "img_url": "https://pgw.udn.com.tw/gw/photo.php?u=https://uc.udn.com.tw/photo/2025/01/18/realtime/31311667.jpg&s=Y&x=0&y=0&sw=2500&sh=1705&exp=3600&w=300",
            "title": "川普與習近平通話 同意建立戰略通話",
            "link": "https://udn.com//news/story/121777/8498171?from=udn-ch1_breaknews-1-0-news",
            "time": "2025-01-18 06:41"
        },
        {
            "img_url": "https://pgw.udn.com.tw/gw/photo.php?u=https://uc.udn.com.tw/photo/2025/01/18/realtime/31313182.jpg&s=Y&x=0&y=0&sw=5079&sh=3386&exp=3600&w=300",
            "title": "學測／決戰理組！首日數A、自然科登場 注意事項一次看",
            "link": "https://udn.com//news/story/124303/8498277?from=udn-ch1_breaknews-1-0-news",
            "time": "2025-01-18 06:30"
        },
        {
            "img_url": "https://pgw.udn.com.tw/gw/photo.php?u=https://uc.udn.com.tw/photo/2025/01/18/realtime/31313174.jpg&s=Y&x=0&y=16&sw=1600&sh=1066&exp=3600&w=300",
            "title": "最新天氣展望 氣象署：1月下半月偏冷時間長、雨量偏少",
            "link": "https://udn.com//news/story/7266/8498276?from=udn-ch1_breaknews-1-0-news",
            "time": "2025-01-18 06:27"
        }
    ]
}