{
    "即時": [
        {
            "img_url": "https://pgw.udn.com.tw/gw/photo.php?u=https://uc.udn.com.tw/photo/2025/06/27/realtime/32384791.jpg&s=Y&x=124&y=0&sw=2790&sh=1860&exp=3600&w=300",
            "title": "對等關稅有機會延期 川普：美中已達成貿易協議",
            "link": "https://udn.com//news/story/6813/8834383?from=udn-ch1_breaknews-1-0-news",
            "time": "2025-06-27 07:11"
        },
        {
            "img_url": "https://pgw.udn.com.tw/gw/photo.php?u=https://uc.udn.com.tw/photo/2025/06/27/realtime/32384783.jpg&s=Y&x=0&y=0&sw=4300&sh=2867&exp=3600&w=300",
            "title": "冷心低壓今將通過台灣 專家：南部注意旺盛午後熱對流",
            "link": "https://udn.com//news/story/7266/8834382?from=udn-ch1_breaknews-1-0-news",
            "time": "2025-06-27 07:09"
        },
        {
            "img_url": "https://pgw.udn.com.tw/gw/photo.php?u=https://uc.udn.com.tw/photo/2025/06/26/0/32377282.jpg&s=Y&x=0&y=0&sw=1280&sh=853&exp=3600&w=300",
            "title": "台鐵漲價很有感！短程漲幅近5成原因曝 客人流失2%新董座反說策略成功？",
            "link": "https://udn.com//news/story/7266/8833012?from=udn-ch1_breaknews-1-0-news",
            "time": "2025-06-27 07:07"
        },
        {
            "img_url": "https://pgw.udn.com.tw/gw/photo.php?u=https://uc.udn.com.tw/photo/2025/06/17/realtime/32322498.jpg&s=Y&x=0&y=0&sw=5471&sh=3647&exp=3600&w=300",
            "title": "房市買氣急凍 剛需族能進場了？理財專家寫給自住客的買屋4攻略必看",
            "link": "https://udn.com//news/story/124300/8834363?from=udn-ch1_breaknews-1-0-news",
            "time": "2025-06-27 07:00"
        },
        {
            "img_url": "https://pgw.udn.com.tw/gw/photo.php?u=https://uc.udn.com.tw/photo/2025/06/26/0/32381147.jpg&s=Y&x=0&y=0&sw=1280&sh=853&exp=3600&w=300",
            "title": "用16順位提前選楊瀚森 拓荒者是豪賭還是神操作？",
            "link": "https://udn.com//news/story/122629/8833524?from=udn-ch1_breaknews-1-0-news",
            "time": "2025-06-27 07:00"
        }
    ]
}