{
    "即時": [
        {
            "img_url": "https://pgw.udn.com.tw/gw/photo.php?u=https://uc.udn.com.tw/photo/2025/02/25/98/31557971.jpg&x=&y=&sw=&sh=&exp=3600&w=300",
            "title": "詐騙園區獲釋近7000人滯留泰緬邊境 泰國盼各國盡速遣返",
            "link": "https://udn.com//news/story/6809/8571090?from=udn-ch1_breaknews-1-0-news",
            "time": "2025-02-25 20:28"
        },
        {
            "img_url": "https://pgw.udn.com.tw/gw/photo.php?u=https://uc.udn.com.tw/photo/2025/02/25/0/31557881.jpg&s=Y&x=0&y=0&sw=1280&sh=853&exp=3600&w=300",
            "title": "經典賽Live／4局下徐若熙飆157公里賞三上三下 中華3：2西班牙",
            "link": "https://udn.com//news/story/10785/8570849?from=udn-ch1_breaknews-1-0-news",
            "time": "2025-02-25 20:26"
        },
        {
            "img_url": "https://pgw.udn.com.tw/gw/photo.php?u=https://uc.udn.com.tw/photo/2025/02/25/realtime/31557966.jpg&s=Y&x=0&y=0&sw=6000&sh=4000&exp=3600&w=300",
            "title": "經典賽／莊陳仲敖3局失2分飆速155公里收工 領先交棒徐若熙",
            "link": "https://udn.com//news/story/10785/8571281?from=udn-ch1_breaknews-1-0-news",
            "time": "2025-02-25 20:24"
        },
        {
            "img_url": "https://pgw.udn.com.tw/gw/photo.php?u=https://uc.udn.com.tw/photo/2025/02/25/realtime/31557963.jpg&s=Y&x=426&y=0&sw=4620&sh=3080&exp=3600&w=300",
            "title": "「tsmc」Logo掛上去了 台積電高雄F22廠掛牌",
            "link": "https://udn.com//news/story/7240/8571279?from=udn-ch1_breaknews-1-0-news",
            "time": "2025-02-25 20:23"
        },
        {
            "img_url": "https://pgw.udn.com.tw/gw/photo.php?u=https://uc.udn.com.tw/photo/2024/12/06/0/31038357.jpg&s=Y&x=0&y=0&sw=1278&sh=852&exp=3600&w=300",
            "title": "NBA／沃神拍賣記者證與爆料用手機 替母校球隊籌措經費",
            "link": "https://udn.com//news/story/7002/8571246?from=udn-ch1_breaknews-1-0-news",
            "time": "2025-02-25 20:20"
        }
    ]
}