{
    "要聞": [
        {
            "img_url": "https://pgw.udn.com.tw/gw/photo.php?u=https://uc.udn.com.tw/photo/2025/04/02/realtime/31770257.jpg&s=Y&x=0&y=10&sw=1373&sh=914&exp=3600&w=300",
            "title": "影／花蓮議長表態罷免傅崐萁 綠黨部：罷免已非藍綠問題",
            "link": "https://udn.com//news/story/124323/8649225?from=udn-catebreaknews_ch2",
            "time": "2025-04-02 15:11"
        },
        {
            "img_url": "https://pgw.udn.com.tw/gw/photo.php?u=https://uc.udn.com.tw/photo/2025/04/02/realtime/31770249.jpeg&s=Y&x=0&y=34&sw=4841&sh=3226&exp=3600&w=300",
            "title": "朱立倫：民主自由沒有先決條件 一黨專政才是最大傷害",
            "link": "https://udn.com//news/story/6656/8649224?from=udn-catebreaknews_ch2",
            "time": "2025-04-02 15:09"
        },
        {
            "img_url": "https://pgw.udn.com.tw/gw/photo.php?u=https://uc.udn.com.tw/photo/2025/04/02/realtime/31770184.jpeg&s=Y&x=0&y=196&sw=2365&sh=1577&exp=3600&w=300",
            "title": "譴責中共軍演 朱立倫：民進黨正在一步步引戰毀台",
            "link": "https://udn.com//news/story/6656/8649198?from=udn-catebreaknews_ch2",
            "time": "2025-04-02 15:02"
        },
        {
            "img_url": "https://pgw.udn.com.tw/gw/photo.php?u=https://uc.udn.com.tw/photo/2025/04/02/realtime/31769953.jpg&s=Y&x=0&y=23&sw=3346&sh=2230&exp=3600&w=300",
            "title": "NCC委員批立院不審委員 在野立委齊轟王正嘉造謠",
            "link": "https://udn.com//news/story/7314/8649185?from=udn-catebreaknews_ch2",
            "time": "2025-04-02 15:00"
        },
        {
            "img_url": "https://pgw.udn.com.tw/gw/photo.php?u=https://uc.udn.com.tw/photo/2025/04/02/realtime/31769877.jpg&s=Y&x=0&y=0&sw=1024&sh=683&exp=3600&w=300",
            "title": "經濟部：液化天然氣船均如期靠卸 不受中國軍演影響",
            "link": "https://udn.com//news/story/7314/8649176?from=udn-catebreaknews_ch2",
            "time": "2025-04-02 14:56"
        }
    ]
}