{
    "要聞": [
        {
            "img_url": "https://pgw.udn.com.tw/gw/photo.php?u=https://uc.udn.com.tw/photo/2025/11/16/realtime/33670713.jpg&s=Y&x=0&y=0&sw=4000&sh=2667&exp=3600&w=300",
            "title": "為照顧兒童身心健康 賴清德總統宣布：衛福部將成立「兒童及社會署」",
            "link": "https://udn.com//news/story/7314/9143052?from=udn-catebreaknews_ch2",
            "time": "2025-11-16 16:13"
        },
        {
            "img_url": "https://pgw.udn.com.tw/gw/photo.php?u=https://uc.udn.com.tw/photo/2025/11/16/1/33670632.jpg&s=Y&x=0&y=0&sw=639&sh=426&exp=3600&w=300",
            "title": "再挺沈伯洋挑戰蔣萬安 曹興誠：沈已樹立勇者形象有利勝選北市長",
            "link": "https://udn.com//news/story/124652/9143022?from=udn-catebreaknews_ch2",
            "time": "2025-11-16 15:46"
        },
        {
            "img_url": "https://pgw.udn.com.tw/gw/photo.php?u=https://uc.udn.com.tw/photo/2025/11/16/realtime/33670507.jpg&s=Y&x=0&y=8&sw=1110&sh=740&exp=3600&w=300",
            "title": "蘇澳分洪道工程經費綁在特別預算裡？吳宗憲批卓榮泰：還有沒有良心",
            "link": "https://udn.com//news/story/6656/9142973?from=udn-catebreaknews_ch2",
            "time": "2025-11-16 15:12"
        },
        {
            "img_url": "https://pgw.udn.com.tw/gw/photo.php?u=https://uc.udn.com.tw/photo/2025/11/16/realtime/33670308.jpeg&s=Y&x=0&y=0&sw=2048&sh=1365&exp=3600&w=300",
            "title": "劉世芳拜會證嚴法師 感謝慈濟協助救災盼持續密切合作",
            "link": "https://udn.com//news/story/6656/9142961?from=udn-catebreaknews_ch2",
            "time": "2025-11-16 14:56"
        },
        {
            "img_url": "https://pgw.udn.com.tw/gw/photo.php?u=https://uc.udn.com.tw/photo/2025/11/16/realtime/33670269.jpg&s=Y&x=0&y=61&sw=8160&sh=5440&exp=3600&w=300",
            "title": "被問怎麼看館長風暴？黃國昌：多年前私事搬上檯面 外人不適合評論",
            "link": "https://udn.com//news/story/6656/9142938?from=udn-catebreaknews_ch2",
            "time": "2025-11-16 14:33"
        }
    ]
}