{
    "要聞": [
        {
            "img_url": "https://pgw.udn.com.tw/gw/photo.php?u=https://uc.udn.com.tw/photo/2025/06/01/98/32173577.jpg&s=Y&x=0&y=380&sw=1280&sh=853&exp=3600&w=300",
            "title": "海巡署首邀70名Cosplayer、攝影登雲林艦 福音戰士扮演者：震撼",
            "link": "https://udn.com//news/story/10930/8777841?from=udn-catebreaknews_ch2",
            "time": "2025-06-01 18:39"
        },
        {
            "img_url": "https://pgw.udn.com.tw/gw/photo.php?u=https://uc.udn.com.tw/photo/2025/06/01/realtime/32173576.jpeg&s=Y&x=0&y=0&sw=5472&sh=3648&exp=3600&w=300",
            "title": "現身新北投力挺罷免吳思瑤 黃國昌：要為柯文哲討公道",
            "link": "https://udn.com//news/story/124323/8777895?from=udn-catebreaknews_ch2",
            "time": "2025-06-01 18:33"
        },
        {
            "img_url": "https://pgw.udn.com.tw/gw/photo.php?u=https://uc.udn.com.tw/photo/2025/06/01/realtime/32173575.jpeg&s=Y&x=0&y=0&sw=3936&sh=2624&exp=3600&w=300",
            "title": "罷免藍白合？黃國昌送「包粽掛飾」 賴苡任：目標一致不分黨派",
            "link": "https://udn.com//news/story/124323/8777894?from=udn-catebreaknews_ch2",
            "time": "2025-06-01 18:31"
        },
        {
            "img_url": "https://pgw.udn.com.tw/gw/photo.php?u=https://uc.udn.com.tw/photo/2025/06/01/realtime/32173186.jpeg&s=Y&x=0&y=0&sw=5472&sh=3648&exp=3600&w=300",
            "title": "黃國昌新北投聲援罷瑤 吳思瑤：車站場域是我文化政績",
            "link": "https://udn.com//news/story/124323/8777846?from=udn-catebreaknews_ch2",
            "time": "2025-06-01 18:11"
        },
        {
            "img_url": "https://pgw.udn.com.tw/gw/photo.php?u=https://uc.udn.com.tw/photo/2025/06/01/realtime/32173310.jpg&s=Y&x=0&y=15&sw=2048&sh=1364&exp=3600&w=300",
            "title": "赴日轉交總統親筆信 郭國文：傳承與安倍家族的緣分",
            "link": "https://udn.com//news/story/6656/8777865?from=udn-catebreaknews_ch2",
            "time": "2025-06-01 18:02"
        }
    ]
}