{
    "要聞": [
        {
            "img_url": "https://pgw.udn.com.tw/gw/photo.php?u=https://uc.udn.com.tw/photo/2026/02/23/realtime/34508746.jpeg&s=Y&x=0&y=15&sw=2153&sh=1434&exp=3600&w=300",
            "title": "軍購條例 國民黨將提黨版 列優先法案",
            "link": "https://udn.com//news/story/6656/9340356?from=udn-catebreaknews_ch2",
            "time": "2026-02-24 00:21"
        },
        {
            "img_url": "https://pgw.udn.com.tw/gw/photo.php?u=https://p.udn.com.tw/upf/2017_news/noimg_cid6638_9.jpg&w=300",
            "title": "民進黨討論台北市長參選人 未納賈永婕",
            "link": "https://udn.com//news/story/124652/9340371?from=udn-catebreaknews_ch2",
            "time": "2026-02-24 00:21"
        },
        {
            "img_url": "https://pgw.udn.com.tw/gw/photo.php?u=https://p.udn.com.tw/upf/2017_news/noimg_cid6638_4.jpg&w=300",
            "title": "年底選舉 鄭麗文喊台灣頭贏到台灣尾",
            "link": "https://udn.com//news/story/124652/9340370?from=udn-catebreaknews_ch2",
            "time": "2026-02-24 00:21"
        },
        {
            "img_url": "https://pgw.udn.com.tw/gw/photo.php?u=https://p.udn.com.tw/upf/2017_news/noimg_cid6638_4.jpg&w=300",
            "title": "戒嚴時期政治檔案 國安局全解密移交檔案局",
            "link": "https://udn.com//news/story/6656/9340369?from=udn-catebreaknews_ch2",
            "time": "2026-02-24 00:20"
        },
        {
            "img_url": "https://pgw.udn.com.tw/gw/photo.php?u=https://uc.udn.com.tw/photo/2026/02/23/realtime/34504858.jpg&s=Y&x=0&y=0&sw=4212&sh=2808&exp=3600&w=300",
            "title": "民進黨萬年總召柯建銘 保位戰今揭曉",
            "link": "https://udn.com//news/story/6656/9340364?from=udn-catebreaknews_ch2",
            "time": "2026-02-24 00:20"
        }
    ]
}