{
    "評論": [
        {
            "img_url": "https://pgw.udn.com.tw/gw/photo.php?u=https://uc.udn.com.tw/photo/t3/2026/05/08/34930284.jpg&M=1&s=Y&x=0&y=0&sw=1262&sh=841&exp=3600&w=300",
            "title": "經濟日報社論／正視台灣成美最大貿易逆差國",
            "link": "https://udn.com//news/story/7338/9570787?from=udn-catebreaknews_ch2",
            "time": "2026-06-17 01:12"
        },
        {
            "img_url": "https://pgw.udn.com.tw/gw/photo.php?u=https://uc.udn.com.tw/photo/t3/2026/06/17/35050391.jpg&M=1&s=Y&x=0&y=15&sw=1280&sh=853&exp=3600&w=300",
            "title": "聯合報社論／送美夢、附戰爭，年輕世代會歡呼埋單嗎？",
            "link": "https://udn.com//news/story/7338/9570818?from=udn-catebreaknews_ch2",
            "time": "2026-06-17 00:38"
        },
        {
            "img_url": "https://pgw.udn.com.tw/gw/photo.php?u=https://uc.udn.com.tw/photo/t3/2026/06/17/35050387.jpg&M=1&s=Y&x=0&y=0&sw=1280&sh=853&exp=3600&w=300",
            "title": "聯合報黑白集／鄭主席至少比賴總統強",
            "link": "https://udn.com//news/story/7338/9570820?from=udn-catebreaknews_ch2",
            "time": "2026-06-17 00:36"
        },
        {
            "img_url": "https://pgw.udn.com.tw/gw/photo.php?u=https://uc.udn.com.tw/photo/t3/2026/06/16/35050284.jpg&M=1&x=&y=&sw=&sh=&exp=3600&w=300",
            "title": "登革熱攻陷醫院 防疫快亡羊補牢",
            "link": "https://udn.com//news/story/7339/9570626?from=udn-catebreaknews_ch2",
            "time": "2026-06-17 00:00"
        },
        {
            "img_url": "https://pgw.udn.com.tw/gw/photo.php?u=https://uc.udn.com.tw/photo/t3/2026/06/16/35050279.jpg&M=1&x=&y=&sw=&sh=&exp=3600&w=300",
            "title": "魏國彥／登革熱來了 蚊子比鼠更可怕",
            "link": "https://udn.com//news/story/7340/9570627?from=udn-catebreaknews_ch2",
            "time": "2026-06-17 00:00"
        }
    ]
}