{
    "兩岸": [
        {
            "img_url": "https://pgw.udn.com.tw/gw/photo.php?u=https://uc.udn.com.tw/photo/t3/2026/05/01/34907121.jpg&M=1&x=&y=&sw=&sh=&exp=3600&w=300",
            "title": "香港經濟改善 負資產住宅數目大跌46.4%",
            "link": "https://udn.com//news/story/7333/9475879?from=udn-catebreaknews_ch2",
            "time": "2026-05-01 10:39"
        },
        {
            "img_url": "https://pgw.udn.com.tw/gw/photo.php?u=https://uc.udn.com.tw/photo/t3/2026/05/01/34907058.jpg&M=1&s=Y&x=0&y=0&sw=1277&sh=851&exp=3600&w=300",
            "title": "明年二十一大換屆前 習近平要求幹部敢於鬥爭：老好人決不重用",
            "link": "https://udn.com//news/story/7331/9475855?from=udn-catebreaknews_ch2",
            "time": "2026-05-01 10:13"
        },
        {
            "img_url": "https://pgw.udn.com.tw/gw/photo.php?u=https://uc.udn.com.tw/photo/t3/2026/05/01/34906988.png&M=1&s=Y&x=0&y=0&sw=1271&sh=848&exp=3600&w=300",
            "title": "歐洲議會譴責大陸「民族團結法」 陸駐歐使館反批：惡意抹黑",
            "link": "https://udn.com//news/story/7331/9475806?from=udn-catebreaknews_ch2",
            "time": "2026-05-01 09:49"
        },
        {
            "img_url": "https://pgw.udn.com.tw/gw/photo.php?u=https://uc.udn.com.tw/photo/t3/2026/05/01/34906971.png&M=1&s=Y&x=0&y=0&sw=840&sh=560&exp=3600&w=300",
            "title": "大陸雲南紅河州客車側翻7死12傷 官方查處掛牌督辦",
            "link": "https://udn.com//news/story/7332/9475798?from=udn-catebreaknews_ch2",
            "time": "2026-05-01 09:46"
        },
        {
            "img_url": "https://pgw.udn.com.tw/gw/photo.php?u=https://uc.udn.com.tw/photo/t3/2026/04/30/34904109.jpg&M=2&x=&y=&sw=&sh=&exp=3600&w=300",
            "title": "全球失衡重啟IMF框架能解？周小川博鰲發言的弦外之音",
            "link": "https://udn.com//news/story/7331/9475666?from=udn-catebreaknews_ch2",
            "time": "2026-05-01 07:00"
        }
    ]
}