{
    "兩岸": [
        {
            "img_url": "https://pgw.udn.com.tw/gw/photo.php?u=https://uc.udn.com.tw/photo/t3/2026/05/19/34961793.jpg&M=1&x=&y=&sw=&sh=&exp=3600&w=300",
            "title": "春哥侃陸／中美大交易霧裡看花 三張清單看成果",
            "link": "https://udn.com//news/story/7331/9513481?from=udn-catebreaknews_ch2",
            "time": "2026-05-20 07:00"
        },
        {
            "img_url": "https://pgw.udn.com.tw/gw/photo.php?u=https://uc.udn.com.tw/photo/t3/2026/05/19/34963392.jpg&M=1&s=Y&x=0&y=0&sw=1279&sh=853&exp=3600&w=300",
            "title": "大陸美債持倉 海嘯來最低…規模降至6,523億美元",
            "link": "https://udn.com//news/story/7333/9513230?from=udn-catebreaknews_ch2",
            "time": "2026-05-20 01:54"
        },
        {
            "img_url": "https://pgw.udn.com.tw/gw/photo.php?u=https://uc.udn.com.tw/photo/t3/2026/04/21/34877145.jpg&M=1&s=Y&x=0&y=65&sw=1280&sh=853&exp=3600&w=300",
            "title": "阿里雲火爆 市占第一名…去年衝上38%",
            "link": "https://udn.com//news/story/7333/9513235?from=udn-catebreaknews_ch2",
            "time": "2026-05-20 01:53"
        },
        {
            "img_url": "https://pgw.udn.com.tw/gw/photo.php?u=https://p.udn.com.tw/upf/2017_news/noimg_cid6640_1.jpg&w=300",
            "title": "陸氫能產業深度洗牌 年底四成公司恐消失",
            "link": "https://udn.com//news/story/7333/9513240?from=udn-catebreaknews_ch2",
            "time": "2026-05-20 01:50"
        },
        {
            "img_url": "https://pgw.udn.com.tw/gw/photo.php?u=https://uc.udn.com.tw/photo/t3/2026/05/20/34963597.jpg&M=1&s=Y&x=0&y=0&sw=1269&sh=846&exp=3600&w=300",
            "title": "習普會登場 將簽40項合作",
            "link": "https://udn.com//news/story/7331/9513243?from=udn-catebreaknews_ch2",
            "time": "2026-05-20 01:49"
        }
    ]
}