{
    "兩岸": [
        {
            "img_url": "https://pgw.udn.com.tw/gw/photo.php?u=https://uc.udn.com.tw/photo/2025/07/11/0/32552165.jpg&s=Y&x=0&y=0&sw=1277&sh=852&exp=3600&w=300",
            "title": "在麥當勞大聲看影片！男奇招KO超爆笑 網友爆共鳴分享絕招",
            "link": "https://udn.com//news/story/7332/8935086?from=udn-catebreaknews_ch2",
            "time": "2025-08-12 21:22"
        },
        {
            "img_url": "https://pgw.udn.com.tw/gw/photo.php?u=https://uc.udn.com.tw/photo/2024/09/19/1/30550317.jpg&s=Y&x=0&y=0&sw=1278&sh=852&exp=3600&w=300",
            "title": "慎入！香港驚現怪異蝸牛「不斷點頭」超恐怖 網友揭悲慘真相",
            "link": "https://udn.com//news/story/7332/8935012?from=udn-catebreaknews_ch2",
            "time": "2025-08-12 20:50"
        },
        {
            "img_url": "https://pgw.udn.com.tw/gw/photo.php?u=https://uc.udn.com.tw/photo/2025/08/12/realtime/32889581.jpg&s=Y&x=0&y=0&sw=799&sh=533&exp=3600&w=300",
            "title": "顯著優化推理體驗...華為發表AI黑科技UCM 9月正式開源",
            "link": "https://udn.com//news/story/7333/8935036?from=udn-catebreaknews_ch2",
            "time": "2025-08-12 20:42"
        },
        {
            "img_url": "https://pgw.udn.com.tw/gw/photo.php?u=https://uc.udn.com.tw/photo/2025/08/12/realtime/32889240.jpg&s=Y&x=0&y=0&sw=630&sh=420&exp=3600&w=300",
            "title": "掀起大陸房市危機風暴的中國恒大 終於將在本月25日從港交所下市",
            "link": "https://udn.com//news/story/7333/8934867?from=udn-catebreaknews_ch2",
            "time": "2025-08-12 19:50"
        },
        {
            "img_url": "https://pgw.udn.com.tw/gw/photo.php?u=https://uc.udn.com.tw/photo/wj/realtime/2025/08/12/32883409.jpg&s=Y&x=0&y=9&sw=770&sh=512&exp=3600&w=300",
            "title": "滬神奇農場培育出最大「生物人工心臟」 有節奏跳動著",
            "link": "https://udn.com//news/story/7335/8933135?from=udn-catebreaknews_ch2",
            "time": "2025-08-12 18:30"
        }
    ]
}