{
    "全球": [
        {
            "img_url": "https://pgw.udn.com.tw/gw/photo.php?u=https://p.udn.com.tw/upf/2017_news/noimg_cid7225_2.jpg&w=300",
            "title": "貿易 芬太尼 TikTok：習近平和川普談了什麼？",
            "link": "https://udn.com//news/story/121777/8499678?from=udn-catebreaknews_ch2",
            "time": "2025-01-19 05:47"
        },
        {
            "img_url": "https://pgw.udn.com.tw/gw/photo.php?u=https://p.udn.com.tw/upf/2017_news/noimg_cid7225_8.jpg&w=300",
            "title": "美國商務部向ADI等4家半導體廠商提供2.464億美元補貼",
            "link": "https://udn.com//news/story/6811/8499722?from=udn-catebreaknews_ch2",
            "time": "2025-01-19 05:43"
        },
        {
            "img_url": "https://pgw.udn.com.tw/gw/photo.php?u=https://p.udn.com.tw/upf/2017_news/noimg_cid7225_6.jpg&w=300",
            "title": "加州電池廠大火 1500人疏散",
            "link": "https://udn.com//news/story/6813/8499681?from=udn-catebreaknews_ch2",
            "time": "2025-01-19 04:25"
        },
        {
            "img_url": "https://pgw.udn.com.tw/gw/photo.php?u=https://p.udn.com.tw/upf/2017_news/noimg_cid7225_0.jpg&w=300",
            "title": "停火協議生效 以哈互相放人",
            "link": "https://udn.com//news/story/123777/8499672?from=udn-catebreaknews_ch2",
            "time": "2025-01-19 04:25"
        },
        {
            "img_url": "https://pgw.udn.com.tw/gw/photo.php?u=https://uc.udn.com.tw/photo/2025/01/18/realtime/31319969.jpg&s=Y&x=0&y=0&sw=2126&sh=1417&exp=3600&w=300",
            "title": "羈押庭開庭 尹錫悅現身",
            "link": "https://udn.com//news/story/6809/8499679?from=udn-catebreaknews_ch2",
            "time": "2025-01-19 04:24"
        }
    ]
}