{
    "全球": [
        {
            "img_url": "https://pgw.udn.com.tw/gw/photo.php?u=https://uc.udn.com.tw/photo/2025/10/15/realtime/33369264.jpg&s=Y&x=0&y=0&sw=3799&sh=2532&exp=3600&w=300",
            "title": "美中貿易戰再度激化 華爾街日報：習近平深信川普受不了美股大跌",
            "link": "https://udn.com//news/story/124373/9071129?from=udn-catebreaknews_ch2",
            "time": "2025-10-15 10:41"
        },
        {
            "img_url": "https://pgw.udn.com.tw/gw/photo.php?u=https://uc.udn.com.tw/photo/2025/10/13/realtime/33348843.jpg&s=Y&x=0&y=0&sw=7405&sh=4937&exp=3600&w=300",
            "title": "百老匯18齣新作全賠 《歌劇魅影》音樂劇大師憂前景",
            "link": "https://udn.com//news/story/6809/9066856?from=udn-catebreaknews_ch2",
            "time": "2025-10-15 10:30"
        },
        {
            "img_url": "https://pgw.udn.com.tw/gw/photo.php?u=https://uc.udn.com.tw/photo/2025/10/15/0/33369104.png&s=Y&x=11&y=0&sw=968&sh=645&exp=3600&w=300",
            "title": "捷克也變天了！右翼浪潮再起「本國利益至上」",
            "link": "https://udn.com//news/story/6812/9071077?from=udn-catebreaknews_ch2",
            "time": "2025-10-15 10:28"
        },
        {
            "img_url": "https://pgw.udn.com.tw/gw/photo.php?u=https://uc.udn.com.tw/photo/2025/10/15/realtime/33369043.jpg&s=Y&x=0&y=0&sw=3541&sh=2340&exp=3600&w=300",
            "title": "英國已故首相柴契爾夫人婚外情秘辛！新書揭鐵娘子2段私情",
            "link": "https://udn.com//news/story/6809/9071054?from=udn-catebreaknews_ch2",
            "time": "2025-10-15 10:20"
        },
        {
            "img_url": "https://pgw.udn.com.tw/gw/photo.php?u=https://uc.udn.com.tw/photo/2025/10/15/realtime/33368942.jpg&s=Y&x=0&y=0&sw=7723&sh=5149&exp=3600&w=300",
            "title": "戴蒙示警信貸風險 「看到一隻蟑螂，就表示還有更多」",
            "link": "https://udn.com//news/story/6811/9071015?from=udn-catebreaknews_ch2",
            "time": "2025-10-15 10:09"
        }
    ]
}