{
    "全球": [
        {
            "img_url": "https://pgw.udn.com.tw/gw/photo.php?u=https://p.udn.com.tw/upf/2017_news/noimg_cid7225_7.jpg&w=300",
            "title": "川普挽留馬斯克：只要願意 隨時可以留下來",
            "link": "https://udn.com//news/story/6813/8711834?from=udn-catebreaknews_ch2",
            "time": "2025-05-02 06:00"
        },
        {
            "img_url": "https://pgw.udn.com.tw/gw/photo.php?u=https://uc.udn.com.tw/photo/2025/05/01/realtime/31960568.jpg&s=Y&x=0&y=0&sw=5326&sh=3551&exp=3600&w=300",
            "title": "西葡大停電凸顯電網系統脆弱 台灣能源孤島學到的啟示",
            "link": "https://udn.com//news/story/6811/8711163?from=udn-catebreaknews_ch2",
            "time": "2025-05-02 06:00"
        },
        {
            "img_url": "https://pgw.udn.com.tw/gw/photo.php?u=https://uc.udn.com.tw/photo/2025/04/30/realtime/31955621.jpg&s=Y&x=0&y=0&sw=3000&sh=2000&exp=3600&w=300",
            "title": "日本跟川普談關稅有2王牌 學者警告：別問美國想要什麼",
            "link": "https://udn.com//news/story/6809/8709425?from=udn-catebreaknews_ch2",
            "time": "2025-05-02 06:00"
        },
        {
            "img_url": "https://pgw.udn.com.tw/gw/photo.php?u=https://uc.udn.com.tw/photo/2025/05/02/1/31962583.jpg&s=Y&x=0&y=0&sw=1280&sh=853&exp=3600&w=300",
            "title": "川普就任百天…馬斯克淡出白宮 正副國安顧問傳下台",
            "link": "https://udn.com//news/story/6813/8711986?from=udn-catebreaknews_ch2",
            "time": "2025-05-02 04:29"
        },
        {
            "img_url": "https://pgw.udn.com.tw/gw/photo.php?u=https://uc.udn.com.tw/photo/2025/05/02/1/31962592.jpg&s=Y&x=0&y=0&sw=1280&sh=853&exp=3600&w=300",
            "title": "李在明無罪判決遭撤銷 南韓大選再生變數",
            "link": "https://udn.com//news/story/6809/8711984?from=udn-catebreaknews_ch2",
            "time": "2025-05-02 04:28"
        }
    ]
}