{
    "全球": [
        {
            "img_url": "https://pgw.udn.com.tw/gw/photo.php?u=https://uc.udn.com.tw/photo/2024/09/11/98/30486736.jpg&s=Y&x=0&y=0&sw=1277&sh=852&exp=3600&w=300",
            "title": "美總統大選辯論／賀錦麗普獲好評、川普評價55波 各界反應一次看",
            "link": "https://udn.com//news/story/121777/8221521?from=udn-catebreaknews_ch2",
            "time": "2024-09-11 16:12"
        },
        {
            "img_url": "https://pgw.udn.com.tw/gw/photo.php?u=https://uc.udn.com.tw/photo/2024/09/11/0/30486562.jpg&s=Y&x=0&y=0&sw=1280&sh=853&exp=3600&w=300",
            "title": "美國大選辯論交鋒！川普、賀錦麗比賽誰抗陸 勝負變數仍多",
            "link": "https://udn.com//news/story/121777/8221460?from=udn-catebreaknews_ch2",
            "time": "2024-09-11 15:55"
        },
        {
            "img_url": "https://pgw.udn.com.tw/gw/photo.php?u=https://uc.udn.com.tw/photo/2024/09/11/realtime/30486493.jpg&s=Y&x=0&y=0&sw=7359&sh=4906&exp=3600&w=300",
            "title": "以色列開出新條件！放哈瑪斯首領安全離開加薩 交換停火、人質獲釋",
            "link": "https://udn.com//news/story/123777/8221484?from=udn-catebreaknews_ch2",
            "time": "2024-09-11 15:39"
        },
        {
            "img_url": "https://pgw.udn.com.tw/gw/photo.php?u=https://uc.udn.com.tw/photo/2024/09/11/realtime/30486406.jpg&s=Y&x=0&y=0&sw=5292&sh=3529&exp=3600&w=300",
            "title": "華為三折機想對槓iPhone 16？分析師點出最大罩門在這裡",
            "link": "https://udn.com//news/story/6811/8221448?from=udn-catebreaknews_ch2",
            "time": "2024-09-11 15:28"
        },
        {
            "img_url": "https://pgw.udn.com.tw/gw/photo.php?u=https://uc.udn.com.tw/photo/2024/09/11/0/30486405.png&s=Y&x=0&y=0&sw=1280&sh=853&exp=3600&w=300",
            "title": "解析美國總統辯論：賀錦麗如何「金蟬脫殼」",
            "link": "https://udn.com//news/story/121777/8221446?from=udn-catebreaknews_ch2",
            "time": "2024-09-11 15:27"
        }
    ]
}