{
    "社會": [
        {
            "img_url": "https://pgw.udn.com.tw/gw/photo.php?u=https://uc.udn.com.tw/photo/2025/05/06/realtime/31986206.jpg&s=Y&x=0&y=5&sw=732&sh=488&exp=3600&w=300",
            "title": "廣明併台硝傳內線交易 董事親友7人買賣股票獲利60餘萬元遭起訴",
            "link": "https://udn.com//news/story/7321/8720056?from=udn-catebreaknews_ch2",
            "time": "2025-05-06 11:04"
        },
        {
            "img_url": "https://pgw.udn.com.tw/gw/photo.php?u=https://uc.udn.com.tw/photo/2025/05/06/realtime/31986117.jpg&s=Y&x=0&y=8&sw=1124&sh=748&exp=3600&w=300",
            "title": "涉打死女友棄保潛逃 76行者前總召陳修將落網",
            "link": "https://udn.com//news/story/7320/8719995?from=udn-catebreaknews_ch2",
            "time": "2025-05-06 10:44"
        },
        {
            "img_url": "https://pgw.udn.com.tw/gw/photo.php?u=https://uc.udn.com.tw/photo/2025/05/06/realtime/31985980.jpg&s=Y&x=0&y=11&sw=1479&sh=986&exp=3600&w=300",
            "title": "高雄2月大男嬰趴睡突失去心跳 送醫急救後仍不治",
            "link": "https://udn.com//news/story/7320/8719939?from=udn-catebreaknews_ch2",
            "time": "2025-05-06 10:28"
        },
        {
            "img_url": "https://pgw.udn.com.tw/gw/photo.php?u=https://uc.udn.com.tw/photo/2025/05/06/realtime/31985922.jpg&s=Y&x=0&y=0&sw=1259&sh=857&exp=3600&w=300",
            "title": "案情出現新事證？基隆檢方再度傳訊聲押前民政處長張淵翔",
            "link": "https://udn.com//news/story/7321/8719904?from=udn-catebreaknews_ch2",
            "time": "2025-05-06 10:19"
        },
        {
            "img_url": "https://pgw.udn.com.tw/gw/photo.php?u=https://uc.udn.com.tw/photo/2025/05/06/realtime/31985907.jpg&s=Y&x=0&y=8&sw=1080&sh=720&exp=3600&w=300",
            "title": "影／台中輕熟女上大夜喝酒 開車西屯連撞7機車一人傷",
            "link": "https://udn.com//news/story/7320/8719897?from=udn-catebreaknews_ch2",
            "time": "2025-05-06 10:18"
        }
    ]
}