{
    "地方": [
        {
            "img_url": "https://pgw.udn.com.tw/gw/photo.php?u=https://uc.udn.com.tw/photo/2025/09/05/realtime/33071384.jpg&s=Y&x=0&y=10&sw=1440&sh=960&exp=3600&w=300",
            "title": "高雄美濃變破碎山河 柯志恩痛心質疑：難道政府不知？",
            "link": "https://udn.com//news/story/7327/8986508?from=udn-catebreaknews_ch2",
            "time": "2025-09-05 19:00"
        },
        {
            "img_url": "https://pgw.udn.com.tw/gw/photo.php?u=https://uc.udn.com.tw/photo/2025/09/05/realtime/33071332.jpg&s=Y&x=0&y=30&sw=4032&sh=2688&exp=3600&w=300",
            "title": "澎湖離島首例到院前完成給藥 心肌梗塞男子成功獲救",
            "link": "https://udn.com//news/story/7327/8986492?from=udn-catebreaknews_ch2",
            "time": "2025-09-05 18:47"
        },
        {
            "img_url": "https://pgw.udn.com.tw/gw/photo.php?u=https://uc.udn.com.tw/photo/2025/09/05/realtime/33071230.jpg&s=Y&x=0&y=11&sw=1477&sh=984&exp=3600&w=300",
            "title": "竹北空氣飄異味…竹縣府設通報平台抓臭源 擬發檢舉獎金",
            "link": "https://udn.com//news/story/7324/8986450?from=udn-catebreaknews_ch2",
            "time": "2025-09-05 18:25"
        },
        {
            "img_url": "https://pgw.udn.com.tw/gw/photo.php?u=https://uc.udn.com.tw/photo/2025/09/05/realtime/33071165.jpeg&s=Y&x=0&y=200&sw=2364&sh=1576&exp=3600&w=300",
            "title": "2025新北蛋黃酥節冠軍出爐 創意組融合鐵觀音、水蜜桃奪冠",
            "link": "https://udn.com//news/story/7323/8986425?from=udn-catebreaknews_ch2",
            "time": "2025-09-05 18:15"
        },
        {
            "img_url": "https://pgw.udn.com.tw/gw/photo.php?u=https://uc.udn.com.tw/photo/2025/09/05/realtime/33070873.jpg&s=Y&x=0&y=0&sw=5568&sh=3712&exp=3600&w=300",
            "title": "金門獲贈500只住警器 優先安裝於各弱勢家庭",
            "link": "https://udn.com//news/story/7327/8986366?from=udn-catebreaknews_ch2",
            "time": "2025-09-05 17:51"
        }
    ]
}