{
    "地方": [
        {
            "img_url": "https://pgw.udn.com.tw/gw/photo.php?u=https://uc.udn.com.tw/photo/2025/05/05/realtime/31982063.jpg&s=Y&x=315&y=0&sw=3402&sh=2268&exp=3600&w=300",
            "title": "彰化八卦山牌樓挨撞該拆？警回應：應依導引、減速",
            "link": "https://udn.com//news/story/7325/8718375?from=udn-catebreaknews_ch2",
            "time": "2025-05-05 15:10"
        },
        {
            "img_url": "https://pgw.udn.com.tw/gw/photo.php?u=https://uc.udn.com.tw/photo/2025/05/04/realtime/31974262.jpg&s=Y&x=44&y=192&sw=1375&sh=917&exp=3600&w=300",
            "title": "媽祖遶境破萬人…他納悶「大家都不上班？」 過來人見怪不怪",
            "link": "https://udn.com//news/story/10906/8718263?from=udn-catebreaknews_ch2",
            "time": "2025-05-05 14:36"
        },
        {
            "img_url": "https://pgw.udn.com.tw/gw/photo.php?u=https://uc.udn.com.tw/photo/2025/05/05/realtime/31981691.jpg&s=Y&x=133&y=0&sw=1440&sh=960&exp=3600&w=300",
            "title": "白沙屯媽祖進香她飽受批評 媽祖停不停縣府引關注 張麗善今吐心聲",
            "link": "https://udn.com//news/story/10906/8718304?from=udn-catebreaknews_ch2",
            "time": "2025-05-05 14:31"
        },
        {
            "img_url": "https://pgw.udn.com.tw/gw/photo.php?u=https://uc.udn.com.tw/photo/2025/05/05/realtime/31981619.png&s=Y&x=245&y=0&sw=1005&sh=670&exp=3600&w=300",
            "title": "違法日租套房誆稱居家共享 北市強力稽查最重可罰200萬",
            "link": "https://udn.com//news/story/7323/8718270?from=udn-catebreaknews_ch2",
            "time": "2025-05-05 14:18"
        },
        {
            "img_url": "https://pgw.udn.com.tw/gw/photo.php?u=https://uc.udn.com.tw/photo/2025/05/05/realtime/31981536.jpg&s=Y&x=0&y=224&sw=873&sh=582&exp=3600&w=300",
            "title": "中市知名登山步道滿是荔枝椿象 市府將用這兩招雙管齊下",
            "link": "https://udn.com//news/story/7325/8718236?from=udn-catebreaknews_ch2",
            "time": "2025-05-05 14:06"
        }
    ]
}