{
    "產經": [
        {
            "img_url": "https://pgw.udn.com.tw/gw/photo.php?u=https://uc.udn.com.tw/photo/2025/01/24/realtime/31374984.png&s=Y&x=42&y=0&sw=1512&sh=1008&exp=3600&w=300",
            "title": "台電今年舉債1500億 創新高",
            "link": "https://udn.com//news/story/7238/8522899?from=udn-catebreaknews_ch2",
            "time": "2025-02-03 01:14"
        },
        {
            "img_url": "https://pgw.udn.com.tw/gw/photo.php?u=https://uc.udn.com.tw/photo/2025/02/02/realtime/31426469.jpg&s=Y&x=0&y=12&sw=1417&sh=944&exp=3600&w=300",
            "title": "撥補台電攻防 平均電價恐漲6.6%",
            "link": "https://udn.com//news/story/7238/8522874?from=udn-catebreaknews_ch2",
            "time": "2025-02-03 01:14"
        },
        {
            "img_url": "https://pgw.udn.com.tw/gw/photo.php?u=https://uc.udn.com.tw/photo/2025/02/02/realtime/31426459.jpg&s=Y&x=0&y=9&sw=1280&sh=852&exp=3600&w=300",
            "title": "昕力資訊越南佈局再擴大 砸重金收購當地軟體業者",
            "link": "https://udn.com//news/story/7240/8522857?from=udn-catebreaknews_ch2",
            "time": "2025-02-02 22:43"
        },
        {
            "img_url": "https://pgw.udn.com.tw/gw/photo.php?u=https://uc.udn.com.tw/photo/2025/02/02/realtime/31426421.jpg&s=Y&x=0&y=0&sw=799&sh=534&exp=3600&w=300",
            "title": "川普政府關稅大刀下一波砍向台灣？ 經濟部回應了",
            "link": "https://udn.com//news/story/7238/8522830?from=udn-catebreaknews_ch2",
            "time": "2025-02-02 22:25"
        },
        {
            "img_url": "https://pgw.udn.com.tw/gw/photo.php?u=https://uc.udn.com.tw/photo/2025/02/02/2/31426351.jpg&x=&y=&sw=&sh=&exp=3600&w=300",
            "title": "微型保險去年順利達標 壽險整體達成率111.9%",
            "link": "https://udn.com//news/story/7239/8522799?from=udn-catebreaknews_ch2",
            "time": "2025-02-02 21:36"
        }
    ]
}