{
    "產經": [
        {
            "img_url": "https://pgw.udn.com.tw/gw/photo.php?u=https://uc.udn.com.tw/photo/2025/01/16/realtime/31298735.jpg&s=Y&x=0&y=23&sw=3372&sh=2248&exp=3600&w=300",
            "title": "黃仁勳回台必訪夜市 傳出今晚逛逢甲夜市吃章魚燒",
            "link": "https://udn.com//news/story/7240/8494833?from=udn-catebreaknews_ch2",
            "time": "2025-01-16 17:13"
        },
        {
            "img_url": "https://pgw.udn.com.tw/gw/photo.php?u=https://uc.udn.com.tw/photo/2025/01/16/realtime/31298656.jpg&s=Y&x=0&y=0&sw=1585&sh=1033&exp=3600&w=300",
            "title": "金管會開放跨業合作 34家保經公司可進軍保險金信託業務",
            "link": "https://udn.com//news/story/7239/8494814?from=udn-catebreaknews_ch2",
            "time": "2025-01-16 17:03"
        },
        {
            "img_url": "https://pgw.udn.com.tw/gw/photo.php?u=https://uc.udn.com.tw/photo/2025/01/16/realtime/31298601.jpg&s=Y&x=0&y=23&sw=3372&sh=2248&exp=3600&w=300",
            "title": "爭搶設輝達海外總部 新北：對方要求高建蔽率、蓋蛋型建物",
            "link": "https://udn.com//news/story/124336/8494802?from=udn-catebreaknews_ch2",
            "time": "2025-01-16 17:00"
        },
        {
            "img_url": "https://pgw.udn.com.tw/gw/photo.php?u=https://uc.udn.com.tw/photo/2025/01/16/realtime/31298558.jpg&s=Y&x=992&y=1332&sw=2538&sh=1692&exp=3600&w=300",
            "title": "何時見黃仁勳？台積電魏哲家今晚行程曝光出現在這",
            "link": "https://udn.com//news/story/124336/8494785?from=udn-catebreaknews_ch2",
            "time": "2025-01-16 16:54"
        },
        {
            "img_url": "https://pgw.udn.com.tw/gw/photo.php?u=https://uc.udn.com.tw/photo/2025/01/16/anntw/31298314.jpg&s=Y&x=0&y=4&sw=562&sh=374&exp=3600&w=300",
            "title": "美商對台投資信心增 但82%擔心能源供應",
            "link": "https://udn.com//news/story/7238/8494727?from=udn-catebreaknews_ch2",
            "time": "2025-01-16 16:51"
        }
    ]
}