{
    "產經": [
        {
            "img_url": "https://pgw.udn.com.tw/gw/photo.php?u=https://uc.udn.com.tw/photo/2025/03/07/0/31616756.jpg&s=Y&x=0&y=0&sw=1080&sh=720&exp=3600&w=300",
            "title": "大罷工！ 8千輛計程車上街抗議Uber、封鎖道路圓環 市區交通陷停擺",
            "link": "https://udn.com//news/story/121591/8593804?from=udn-catebreaknews_ch2",
            "time": "2025-03-09 06:00"
        },
        {
            "img_url": "https://pgw.udn.com.tw/gw/photo.php?u=https://uc.udn.com.tw/photo/2025/03/08/realtime/31621795.png&s=Y&x=0&y=23&sw=3333&sh=2222&exp=3600&w=300",
            "title": "金融業拚AI阻詐 一圖看警示帳戶連年攀高、詐騙手法前5名",
            "link": "https://udn.com//news/story/7239/8595464?from=udn-catebreaknews_ch2",
            "time": "2025-03-09 05:50"
        },
        {
            "img_url": "https://pgw.udn.com.tw/gw/photo.php?u=https://uc.udn.com.tw/photo/2025/03/07/0/31616592.jpg&s=Y&x=0&y=0&sw=957&sh=638&exp=3600&w=300",
            "title": "百事可樂發起「百事挑戰」 大成功 可口可樂緊張到宣布要改變配方",
            "link": "https://udn.com//news/story/121591/8593722?from=udn-catebreaknews_ch2",
            "time": "2025-03-09 05:00"
        },
        {
            "img_url": "https://pgw.udn.com.tw/gw/photo.php?u=https://uc.udn.com.tw/photo/2025/02/19/realtime/31522290.jpg&s=Y&x=89&y=0&sw=4686&sh=3125&exp=3600&w=300",
            "title": "觀察站／拉齊AI戰力 政府應扮神隊友",
            "link": "https://udn.com//news/story/7239/8595381?from=udn-catebreaknews_ch2",
            "time": "2025-03-09 04:03"
        },
        {
            "img_url": "https://pgw.udn.com.tw/gw/photo.php?u=https://uc.udn.com.tw/photo/2025/02/20/0/31526892.jpg&s=Y&x=0&y=0&sw=999&sh=666&exp=3600&w=300",
            "title": "異業聯防 警示帳戶抓一串粽",
            "link": "https://udn.com//news/story/7239/8595379?from=udn-catebreaknews_ch2",
            "time": "2025-03-09 04:00"
        }
    ]
}