{
    "產經": [
        {
            "img_url": "https://pgw.udn.com.tw/gw/photo.php?u=https://uc.udn.com.tw/photo/2025/02/01/realtime/31422010.jpg&s=Y&x=0&y=0&sw=1585&sh=1033&exp=3600&w=300",
            "title": "兩大社群詐騙氾濫！常見詐團手法曝光 金管會籲民眾提高警覺",
            "link": "https://udn.com//news/story/7238/8521610?from=udn-catebreaknews_ch2",
            "time": "2025-02-01 20:48"
        },
        {
            "img_url": "https://pgw.udn.com.tw/gw/photo.php?u=https://uc.udn.com.tw/photo/2025/02/01/0/31421336.jpg&s=Y&x=0&y=0&sw=1277&sh=852&exp=3600&w=300",
            "title": "川普2.0貿易戰風雨欲來 台灣恐也被加徵關稅？專家：應4面向因應",
            "link": "https://udn.com//news/story/7238/8521519?from=udn-catebreaknews_ch2",
            "time": "2025-02-01 18:36"
        },
        {
            "img_url": "https://pgw.udn.com.tw/gw/photo.php?u=https://uc.udn.com.tw/photo/2025/02/01/2/31421525.png&s=Y&x=44&y=0&sw=1080&sh=720&exp=3600&w=300",
            "title": "配合春節穩定物價！中油宣布：2月家庭用桶裝瓦斯凍漲",
            "link": "https://udn.com//news/story/7238/8521512?from=udn-catebreaknews_ch2",
            "time": "2025-02-01 17:49"
        },
        {
            "img_url": "https://pgw.udn.com.tw/gw/photo.php?u=https://uc.udn.com.tw/photo/2025/02/01/98/31421331.jpg&s=Y&x=0&y=0&sw=1277&sh=852&exp=3600&w=300",
            "title": "中油：配合春節期間穩定物價 2月桶裝瓦斯凍漲",
            "link": "https://udn.com//news/story/7238/8521441?from=udn-catebreaknews_ch2",
            "time": "2025-02-01 16:36"
        },
        {
            "img_url": "https://pgw.udn.com.tw/gw/photo.php?u=https://uc.udn.com.tw/photo/2025/02/01/realtime/31419904.jpg&s=Y&x=0&y=17&sw=2364&sh=1576&exp=3600&w=300",
            "title": "國家住都中心推都更 今年再推北市精華區五大都更案",
            "link": "https://udn.com//news/story/7238/8521355?from=udn-catebreaknews_ch2",
            "time": "2025-02-01 14:36"
        }
    ]
}