{
    "股市": [
        {
            "img_url": "https://pgw.udn.com.tw/gw/photo.php?u=https://uc.udn.com.tw/photo/2024/12/17/realtime/31106937.jpg&s=Y&x=0&y=0&sw=1889&sh=1259&exp=3600&w=300",
            "title": "外資買超392億元 買遠東新最多、群創及友達也獲青睞",
            "link": "https://udn.com//news/story/7251/8444092?from=udn-catebreaknews_ch2",
            "time": "2024-12-23 17:19"
        },
        {
            "img_url": "https://pgw.udn.com.tw/gw/photo.php?u=https://uc.udn.com.tw/photo/2024/12/20/2/31122589.jpg&s=Y&x=64&y=0&sw=1157&sh=771&exp=3600&w=300",
            "title": "全球股票型基金規模成長 這檔今年來規模增胖居冠",
            "link": "https://udn.com//news/story/7251/8443940?from=udn-catebreaknews_ch2",
            "time": "2024-12-23 16:17"
        },
        {
            "img_url": "https://pgw.udn.com.tw/gw/photo.php?u=https://uc.udn.com.tw/photo/2024/12/19/realtime/31117519.jpg&s=Y&x=0&y=0&sw=4815&sh=3260&exp=3600&w=300",
            "title": "福懋油經營權之爭暫落幕 股價爆量跌停寫3年新低",
            "link": "https://udn.com//news/story/7252/8443865?from=udn-catebreaknews_ch2",
            "time": "2024-12-23 15:59"
        },
        {
            "img_url": "https://pgw.udn.com.tw/gw/photo.php?u=https://uc.udn.com.tw/photo/2024/12/12/2/31076384.jpg&s=Y&x=0&y=0&sw=1281&sh=854&exp=3600&w=300",
            "title": "新手想存ETF沒有方向？存股哥舉00878為例：先達「季配三萬元」為目標",
            "link": "https://udn.com//news/story/123006/8443765?from=udn-catebreaknews_ch2",
            "time": "2024-12-23 15:30"
        },
        {
            "img_url": "https://pgw.udn.com.tw/gw/photo.php?u=https://uc.udn.com.tw/photo/2024/12/11/0/31072933.jpg&s=Y&x=0&y=0&sw=1253&sh=835&exp=3600&w=300",
            "title": "00757巨頭們打成一包做ETF…波動高於美股！ 真星華：高報酬高風險",
            "link": "https://udn.com//news/story/123006/8443717?from=udn-catebreaknews_ch2",
            "time": "2024-12-23 15:14"
        }
    ]
}