{
    "股市": [
        {
            "img_url": "https://pgw.udn.com.tw/gw/photo.php?u=https://uc.udn.com.tw/photo/2025/10/13/98/33349295.jpg&s=Y&x=0&y=0&sw=1280&sh=853&exp=3600&w=300",
            "title": "國泰金（2882）迎落後補漲行情？專家指「3關鍵」：有滿足上漲就只等時間",
            "link": "https://udn.com//news/story/7251/9081566?from=udn-catebreaknews_ch2",
            "time": "2025-10-20 11:13"
        },
        {
            "img_url": "https://pgw.udn.com.tw/gw/photo.php?u=https://uc.udn.com.tw/photo/2025/10/20/0/33417290.jpg&x=&y=&sw=&sh=&exp=3600&w=300",
            "title": "一年半成長161萬…靠「借貸存股」滾出穩定現金流！存股哥公開成果",
            "link": "https://udn.com//news/story/12806/9081507?from=udn-catebreaknews_ch2",
            "time": "2025-10-20 11:06"
        },
        {
            "img_url": "https://pgw.udn.com.tw/gw/photo.php?u=https://uc.udn.com.tw/photo/2025/10/20/realtime/33417062.png&s=Y&x=89&y=0&sw=372&sh=249&exp=3600&w=300",
            "title": "台股基金9月定期定額衝破50萬筆 這檔近一年績效狂漲38%奪人氣王",
            "link": "https://udn.com//news/story/10103/9081505?from=udn-catebreaknews_ch2",
            "time": "2025-10-20 10:44"
        },
        {
            "img_url": "https://pgw.udn.com.tw/gw/photo.php?u=https://uc.udn.com.tw/photo/2025/10/20/0/33416936.jpg&x=&y=&sw=&sh=&exp=3600&w=300",
            "title": "巴菲特都推薦ETF所以散戶只要買0050就好？陳重銘：忽略了兩個盲點",
            "link": "https://udn.com//news/story/123006/9081452?from=udn-catebreaknews_ch2",
            "time": "2025-10-20 10:34"
        },
        {
            "img_url": "https://pgw.udn.com.tw/gw/photo.php?u=https://uc.udn.com.tw/photo/2025/10/17/0/33387818.jpg&s=Y&x=64&y=0&sw=1160&sh=773&exp=3600&w=300",
            "title": "台積電劍指1,500元、盤中衝達1,495元追平天價 貢獻大盤指數逾370點",
            "link": "https://udn.com//news/story/7251/9081464?from=udn-catebreaknews_ch2",
            "time": "2025-10-20 10:29"
        }
    ]
}