{
    "生活": [
        {
            "img_url": "https://pgw.udn.com.tw/gw/photo.php?u=https://uc.udn.com.tw/photo/2025/08/11/realtime/32875071.jpg&s=Y&x=0&y=7&sw=1108&sh=738&exp=3600&w=300",
            "title": "社區遊戲室竟窩藏龜殼花！5歲男童被咬傷 捕蛇時地板還見血跡",
            "link": "https://udn.com//news/story/7470/8931035?from=udn-catebreaknews_ch2",
            "time": "2025-08-11 11:33"
        },
        {
            "img_url": "https://pgw.udn.com.tw/gw/photo.php?u=https://uc.udn.com.tw/photo/2025/08/11/realtime/32874967.jpg&s=Y&x=48&y=0&sw=1311&sh=874&exp=3600&w=300",
            "title": "區間車突停駛路竹「乘客傻眼車廂黑一片」台鐵致歉了",
            "link": "https://udn.com//news/story/7266/8930987?from=udn-catebreaknews_ch2",
            "time": "2025-08-11 11:18"
        },
        {
            "img_url": "https://pgw.udn.com.tw/gw/photo.php?u=https://uc.udn.com.tw/photo/2025/08/11/realtime/32874943.jpeg&s=Y&x=0&y=0&sw=1842&sh=1228&exp=3600&w=300",
            "title": "楊柳颱風估周三午登陸花東傍晚離陸 氣象署今深夜到明天發海警陸警",
            "link": "https://udn.com//news/story/7266/8930976?from=udn-catebreaknews_ch2",
            "time": "2025-08-11 11:14"
        },
        {
            "img_url": "https://pgw.udn.com.tw/gw/photo.php?u=https://uc.udn.com.tw/photo/2025/08/11/realtime/32874905.png&s=Y&x=68&y=0&sw=864&sh=576&exp=3600&w=300",
            "title": "麥當勞「麥脆鷄腿、勁辣鷄腿堡」2件99元！拿坡里「披薩買1送1」",
            "link": "https://udn.com//news/story/124378/8930959?from=udn-catebreaknews_ch2",
            "time": "2025-08-11 11:06"
        },
        {
            "img_url": "https://pgw.udn.com.tw/gw/photo.php?u=https://uc.udn.com.tw/photo/2025/08/11/realtime/32874772.jpg&s=Y&x=0&y=0&sw=1322&sh=881&exp=3600&w=300",
            "title": "不要一直滑手機！烏龜頸年輕化 醫：小心脖子後面長出「富貴包」",
            "link": "https://udn.com//news/story/7266/8930910?from=udn-catebreaknews_ch2",
            "time": "2025-08-11 10:54"
        }
    ]
}