{
    "生活": [
        {
            "img_url": "https://pgw.udn.com.tw/gw/photo.php?u=https://uc.udn.com.tw/photo/2026/01/02/0/34090644.jpg&s=Y&x=0&y=0&sw=800&sh=533&exp=3600&w=300",
            "title": "微短劇正夯！《世世動了心》1月5日首播",
            "link": "https://udn.com//news/story/7266/9240920?from=udn-catebreaknews_ch2",
            "time": "2026-01-02 15:16"
        },
        {
            "img_url": "https://pgw.udn.com.tw/gw/photo.php?u=https://uc.udn.com.tw/photo/2026/01/02/0/34089985.jpg&s=Y&x=136&y=108&sw=1041&sh=694&exp=3600&w=300",
            "title": "自助餐熱量炸彈！營養師曝白帶魚像「吸油海綿」 2招減負擔",
            "link": "https://udn.com//news/story/7266/9240666?from=udn-catebreaknews_ch2",
            "time": "2026-01-02 15:03"
        },
        {
            "img_url": "https://pgw.udn.com.tw/gw/photo.php?u=https://uc.udn.com.tw/photo/2026/01/02/0/34090352.jpg&s=Y&x=0&y=0&sw=792&sh=528&exp=3600&w=300",
            "title": "Threads上最夯的台灣「特權量表」是什麼？一次看懂",
            "link": "https://udn.com//news/story/7266/9240859?from=udn-catebreaknews_ch2",
            "time": "2026-01-02 15:01"
        },
        {
            "img_url": "https://pgw.udn.com.tw/gw/photo.php?u=https://uc.udn.com.tw/photo/2026/01/02/realtime/34090370.jpg&s=Y&x=0&y=0&sw=799&sh=523&exp=3600&w=300",
            "title": "桃客運將打人... 桃園培訓公車司機加嚴要先看「良民證」",
            "link": "https://udn.com//news/story/7266/9240878?from=udn-catebreaknews_ch2",
            "time": "2026-01-02 14:57"
        },
        {
            "img_url": "https://pgw.udn.com.tw/gw/photo.php?u=https://uc.udn.com.tw/photo/2026/01/02/0/34090135.jpg&s=Y&x=0&y=0&sw=1280&sh=853&exp=3600&w=300",
            "title": "新年初夢驚魂別擔心！夢見「火災」能量爆發 1內容象徵大轉運",
            "link": "https://udn.com//news/story/7268/9240750?from=udn-catebreaknews_ch2",
            "time": "2026-01-02 14:54"
        }
    ]
}