{
    "生活": [
        {
            "img_url": "https://pgw.udn.com.tw/gw/photo.php?u=https://uc.udn.com.tw/photo/2024/11/24/0/30963957.jpg&s=Y&x=0&y=0&sw=1280&sh=853&exp=3600&w=300",
            "title": "妹婿借住還霸佔車庫嗆「先停先贏」 母竟力挺：要趕他先趕我走",
            "link": "https://udn.com//news/story/7272/8381154?from=udn-catebreaknews_ch2",
            "time": "2024-11-24 13:06"
        },
        {
            "img_url": "https://pgw.udn.com.tw/gw/photo.php?u=https://uc.udn.com.tw/photo/2024/11/23/realtime/30959124.jpg&s=Y&x=0&y=17&sw=2272&sh=1514&exp=3600&w=300",
            "title": "台版數位佛典CBETA享譽國際 大陸借助AI推新版成挑戰？",
            "link": "https://udn.com//news/story/7266/8380029?from=udn-catebreaknews_ch2",
            "time": "2024-11-24 13:00"
        },
        {
            "img_url": "https://pgw.udn.com.tw/gw/photo.php?u=https://uc.udn.com.tw/photo/2024/11/24/98/30964131.jpg&s=Y&x=108&y=0&sw=1056&sh=704&exp=3600&w=300",
            "title": "中東第2家！阿提哈德航空獲准2025飛台",
            "link": "https://udn.com//news/story/7266/8381203?from=udn-catebreaknews_ch2",
            "time": "2024-11-24 12:59"
        },
        {
            "img_url": "https://pgw.udn.com.tw/gw/photo.php?u=https://uc.udn.com.tw/photo/2024/11/24/realtime/30964051.jpg&s=Y&x=0&y=0&sw=2508&sh=1672&exp=3600&w=300",
            "title": "12歲女童反覆頭痛、嘔吐 竟是腦中有4公分大腫瘤",
            "link": "https://udn.com//news/story/7266/8381177?from=udn-catebreaknews_ch2",
            "time": "2024-11-24 12:42"
        },
        {
            "img_url": "https://pgw.udn.com.tw/gw/photo.php?u=https://uc.udn.com.tw/photo/2024/11/24/0/30963895.jpg&s=Y&x=4&y=0&sw=1277&sh=852&exp=3600&w=300",
            "title": "靜電恐是健康警訊！ 營養師提醒出現「6種」情況者多加留意",
            "link": "https://udn.com//news/story/7266/8381116?from=udn-catebreaknews_ch2",
            "time": "2024-11-24 12:39"
        }
    ]
}