{
    "生活": [
        {
            "img_url": "https://pgw.udn.com.tw/gw/photo.php?u=https://uc.udn.com.tw/photo/2025/07/31/realtime/32774446.jpg&s=Y&x=0&y=0&sw=5472&sh=3648&exp=3600&w=300",
            "title": "失智症百萬新藥納健保？ 石崇良：「這原因」不給付",
            "link": "https://udn.com//news/story/7266/8909410?from=udn-catebreaknews_ch2",
            "time": "2025-07-31 17:20"
        },
        {
            "img_url": "https://pgw.udn.com.tw/gw/photo.php?u=https://uc.udn.com.tw/photo/2025/07/31/realtime/32774110.jpg&s=Y&x=0&y=18&sw=2625&sh=1750&exp=3600&w=300",
            "title": "高醫揭早期荷爾蒙陽性乳癌「5年過關」迷思　持續追蹤成保命關鍵",
            "link": "https://udn.com//news/story/7266/8909341?from=udn-catebreaknews_ch2",
            "time": "2025-07-31 16:55"
        },
        {
            "img_url": "https://pgw.udn.com.tw/gw/photo.php?u=https://uc.udn.com.tw/photo/2025/07/31/realtime/32773816.jpg&s=Y&x=0&y=11&sw=1477&sh=984&exp=3600&w=300",
            "title": "內政部公布今上半年租金統計 全國中位數8500元",
            "link": "https://udn.com//news/story/7266/8909280?from=udn-catebreaknews_ch2",
            "time": "2025-07-31 16:35"
        },
        {
            "img_url": "https://pgw.udn.com.tw/gw/photo.php?u=https://uc.udn.com.tw/photo/2025/07/31/realtime/32773786.png&s=Y&x=0&y=0&sw=1300&sh=880&exp=3600&w=300",
            "title": "衛福部8月新制一次看！明起門診可打抗生素、「這族群」免費打肺鏈疫苗",
            "link": "https://udn.com//news/story/7266/8909273?from=udn-catebreaknews_ch2",
            "time": "2025-07-31 16:32"
        },
        {
            "img_url": "https://pgw.udn.com.tw/gw/photo.php?u=https://uc.udn.com.tw/photo/2025/07/31/0/32773686.jpg&s=Y&x=0&y=0&sw=1280&sh=853&exp=3600&w=300",
            "title": "為什麼總愛上錯的人？心理學曝：你的愛情觀，藏著童年的影子",
            "link": "https://udn.com//news/story/121484/8909221?from=udn-catebreaknews_ch2",
            "time": "2025-07-31 16:27"
        }
    ]
}